qbittorrent_mcp/__init__.py
qbittorrent_mcp/api.py
qbittorrent_mcp/client.py
qbittorrent_mcp/main.py
iflow_mcp_qbittorrent_mcp-0.1.0.dist-info/METADATA
iflow_mcp_qbittorrent_mcp-0.1.0.dist-info/WHEEL
iflow_mcp_qbittorrent_mcp-0.1.0.dist-info/entry_points.txt
iflow_mcp_qbittorrent_mcp-0.1.0.dist-info/top_level.txt
iflow_mcp_qbittorrent_mcp-0.1.0.dist-info/RECORD
